edgar3/__init__.py
edgar3/edgar.py
edgar3/edgar_index.py
edgar3/filing.py
edgar3/filing_13f.py
edgar3-1.2.1.dist-info/LICENSE
edgar3-1.2.1.dist-info/WHEEL
edgar3-1.2.1.dist-info/METADATA
edgar3-1.2.1.dist-info/RECORD
