Metadata-Version: 2.1
Name: edgar3
Version: 1.2.1
Summary: Simple 13F Edgar Extractor
Author: Ken Farr
Author-email: ken@farr.ai
Requires-Python: >=3.8,<4.0
Classifier: Programming Language :: Python :: 3
Classifier: Programming Language :: Python :: 3.8
Classifier: Programming Language :: Python :: 3.9
Requires-Dist: backoff (>=1.10.0,<2.0.0)
Requires-Dist: httpx (>=0.11.0,<0.12.0)
Requires-Dist: pandas (>=0.25.3,<0.26.0)
